orpc/__init__.py
orpc/asio.py
orpc/client.py
orpc/exceptions.py
orpc/protocol.py
orpc/tests/__init__.py
orpc/tests/test_protocol.py
orpc_client-0.5.13.dist-info/licenses/LICENSE
orpc_client-0.5.13.dist-info/METADATA
orpc_client-0.5.13.dist-info/WHEEL
orpc_client-0.5.13.dist-info/top_level.txt
orpc_client-0.5.13.dist-info/RECORD
